clickshots/__init__.py
clickshots/core.py
clickshots/listeners.py
clickshots/utils.py
clickshots-0.2.0.dist-info/LICENSE
clickshots-0.2.0.dist-info/METADATA
clickshots-0.2.0.dist-info/WHEEL
clickshots-0.2.0.dist-info/entry_points.txt
clickshots-0.2.0.dist-info/top_level.txt
clickshots-0.2.0.dist-info/RECORD
