Metadata-Version: 2.1
Name: clickshots
Version: 0.2.0
Summary: A robust automated screenshot capture system
Home-page: https://github.com/ayon1901/clickshots
Author: Akmol Masud
Author-email: akmolmasud5@gmail.com
Project-URL: Bug Tracker, https://github.com/ayon1901/clickshots/issues
Classifier: Programming Language :: Python :: 3
Classifier: License :: OSI Approved :: MIT License
Classifier: Operating System :: OS Independent
Requires-Python: >=3.8
License-File: LICENSE
Requires-Dist: pynput>=1.7.0
Requires-Dist: Pillow>=9.0.0
Requires-Dist: pyscreenshot>=3.1
Requires-Dist: pyautogui; platform_system == "Darwin"
Requires-Dist: python-xlib; platform_system == "Linux"
Requires-Dist: PyQt5; platform_system == "Linux"
Provides-Extra: test
Requires-Dist: pytest>=7.0; extra == "test"
Requires-Dist: pytest-cov>=4.0; extra == "test"
Requires-Dist: pytest-mock>=3.10; extra == "test"
Requires-Dist: coverage>=7.0; extra == "test"
Requires-Dist: pytest-xvfb; platform_system == "Linux" and extra == "test"
